[{"title":"1946年立春时间是 1946年02月04日 18:03:53 农历： 正月(大)初三"},{"title":"1946年雨水时间是 1946年02月19日 14:08:30 农历： 正月(大)十八"},{"title":"1946年驚蟄时间是 1946年03月06日 12:24:38 农历： 二月(小)初三"},{"title":"1946年春分时间是 1946年03月21日 13:32:37 农历： 二月(小)十八"},{"title":"1946年清明时间是 1946年04月05日 17:38:32 农历： 三月(小)初四"},{"title":"1946年穀雨时间是 1946年04月21日 01:02:08 农历： 三月(小)二十"},{"title":"1946年立夏时间是 1946年05月06日 11:21:29 农历： 四月(大)初六"},{"title":"1946年小滿时间是 1946年05月22日 00:33:53 农历： 四月(大)廿二"},{"title":"1946年芒種时间是 1946年06月06日 15:48:42 农历： 五月(小)初七"},{"title":"1946年夏至时间是 1946年06月22日 08:44:17 农历： 五月(小)廿三"},{"title":"1946年小暑时间是 1946年07月08日 02:10:48 农历： 六月(小)初十"},{"title":"1946年大暑时间是 1946年07月23日 19:37:00 农历： 六月(小)廿五"},{"title":"1946年立秋时间是 1946年08月08日 11:51:35 农历： 七月(大)十二"},{"title":"1946年處暑时间是 1946年08月24日 02:26:19 农历： 七月(大)廿八"},{"title":"1946年白露时间是 1946年09月08日 14:27:25 农历： 八月(小)十三"},{"title":"1946年秋分时间是 1946年09月23日 23:40:34 农历： 八月(小)廿八"},{"title":"1946年寒露时间是 1946年10月09日 05:40:47 农历： 九月(大)十五"},{"title":"1946年霜降时间是 1946年10月24日 08:34:39 农历： 九月(大)三十"},{"title":"1946年立冬时间是 1946年11月08日 08:27:09 农历： 十月(大)十五"},{"title":"1946年小雪时间是 1946年11月23日 05:46:15 农历： 十月(大)三十"},{"title":"1946年大雪时间是 1946年12月08日 01:00:11 农历： 十一月(小)十五"},{"title":"1946年冬至时间是 1946年12月22日 18:53:17 农历： 十一月(小)廿九"},{"title":"1946年小寒时间是 1946年01月06日 06:16:19 农历： 十二月(大)初四"},{"title":"1946年大寒时间是 1946年01月20日 23:44:35 农历： 十二月(大)十八"},{"title":"1945年冬至时间是 1945年12月22日 13:03:32 农历： 十一月(小)十八"},{"title":"1945年小寒时间是 1945年01月06日 00:34:26 农历： 十一月(大)廿三"},{"title":"1945年大寒时间是 1945年01月20日 17:53:36 农历： 十二月(大)初七"}]