[{"title":"1967年立春时间是 1967年02月04日 20:30:49 农历： 十二月(小)廿五"},{"title":"1967年雨水时间是 1967年02月19日 16:23:38 农历： 正月(大)十一"},{"title":"1967年驚蟄时间是 1967年03月06日 14:41:53 农历： 正月(大)廿六"},{"title":"1967年春分时间是 1967年03月21日 15:36:46 农历： 二月(大)十一"},{"title":"1967年清明时间是 1967年04月05日 19:44:41 农历： 二月(大)廿六"},{"title":"1967年穀雨时间是 1967年04月21日 02:55:07 农历： 三月(小)十二"},{"title":"1967年立夏时间是 1967年05月06日 13:17:26 农历： 三月(小)廿七"},{"title":"1967年小滿时间是 1967年05月22日 02:17:52 农历： 四月(大)十四"},{"title":"1967年芒種时间是 1967年06月06日 17:36:18 农历： 四月(大)廿九"},{"title":"1967年夏至时间是 1967年06月22日 10:22:49 农历： 五月(大)十五"},{"title":"1967年小暑时间是 1967年07月08日 03:53:19 农历： 六月(小)初一"},{"title":"1967年大暑时间是 1967年07月23日 21:15:49 农历： 六月(小)十六"},{"title":"1967年立秋时间是 1967年08月08日 13:34:51 农历： 七月(小)初三"},{"title":"1967年處暑时间是 1967年08月24日 04:12:24 农历： 七月(小)十九"},{"title":"1967年白露时间是 1967年09月08日 16:17:42 农历： 八月(大)初五"},{"title":"1967年秋分时间是 1967年09月24日 01:38:01 农历： 八月(大)廿一"},{"title":"1967年寒露时间是 1967年10月09日 07:41:11 农历： 九月(小)初六"},{"title":"1967年霜降时间是 1967年10月24日 10:43:44 农历： 九月(小)廿一"},{"title":"1967年立冬时间是 1967年11月08日 10:37:23 农历： 十月(大)初七"},{"title":"1967年小雪时间是 1967年11月23日 08:04:26 农历： 十月(大)廿二"},{"title":"1967年大雪时间是 1967年12月08日 03:17:28 农历： 十一月(小)初七"},{"title":"1967年冬至时间是 1967年12月22日 21:16:17 农历： 十一月(小)廿一"},{"title":"1967年小寒时间是 1967年01月06日 08:48:19 农历： 十一月(大)廿六"},{"title":"1967年大寒时间是 1967年01月21日 02:07:30 农历： 十二月(小)十一"},{"title":"1966年冬至时间是 1966年12月22日 15:28:08 农历： 十一月(大)十一"},{"title":"1966年小寒时间是 1966年01月06日 02:54:20 农历： 十二月(小)十五"},{"title":"1966年大寒时间是 1966年01月20日 20:19:39 农历： 十二月(小)廿九"}]