[{"title":"2004年立春时间是 2004年02月04日 19:56:13 农历： 正月(小)十四"},{"title":"2004年雨水时间是 2004年02月19日 15:49:59 农历： 正月(小)廿九"},{"title":"2004年驚蟄时间是 2004年03月05日 13:55:38 农历： 二月(大)十五"},{"title":"2004年春分时间是 2004年03月20日 14:48:38 农历： 二月(大)三十"},{"title":"2004年清明时间是 2004年04月04日 18:43:19 农历： 二月(小)十五"},{"title":"2004年穀雨时间是 2004年04月20日 01:50:25 农历： 三月(大)初二"},{"title":"2004年立夏时间是 2004年05月05日 12:02:28 农历： 三月(大)十七"},{"title":"2004年小滿时间是 2004年05月21日 00:59:12 农历： 四月(大)初三"},{"title":"2004年芒種时间是 2004年06月05日 16:13:46 农历： 四月(大)十八"},{"title":"2004年夏至时间是 2004年06月21日 08:56:51 农历： 五月(小)初四"},{"title":"2004年小暑时间是 2004年07月07日 02:31:16 农历： 五月(小)二十"},{"title":"2004年大暑时间是 2004年07月22日 19:50:09 农历： 六月(大)初六"},{"title":"2004年立秋时间是 2004年08月07日 12:19:36 农历： 六月(大)廿二"},{"title":"2004年處暑时间是 2004年08月23日 02:53:15 农历： 七月(小)初八"},{"title":"2004年白露时间是 2004年09月07日 15:12:55 农历： 七月(小)廿三"},{"title":"2004年秋分时间是 2004年09月23日 00:29:50 农历： 八月(大)初十"},{"title":"2004年寒露时间是 2004年10月08日 06:49:18 农历： 八月(大)廿五"},{"title":"2004年霜降时间是 2004年10月23日 09:48:49 农历： 九月(小)初十"},{"title":"2004年立冬时间是 2004年11月07日 09:58:33 农历： 九月(小)廿五"},{"title":"2004年小雪时间是 2004年11月22日 07:21:40 农历： 十月(大)十一"},{"title":"2004年大雪时间是 2004年12月07日 02:48:57 农历： 十月(大)廿六"},{"title":"2004年冬至时间是 2004年12月21日 20:41:36 农历： 十一月(小)初十"},{"title":"2004年小寒时间是 2004年01月06日 08:18:33 农历： 十二月(大)十五"},{"title":"2004年大寒时间是 2004年01月21日 01:42:22 农历： 十二月(大)三十"},{"title":"2003年冬至时间是 2003年12月22日 15:03:48 农历： 十一月(小)廿九"},{"title":"2003年小寒时间是 2003年01月06日 02:27:43 农历： 十二月(小)初四"},{"title":"2003年大寒时间是 2003年01月20日 19:52:35 农历： 十二月(小)十八"}]