[{"title":"2013年立春时间是 2013年02月04日 00:13:25 农历： 十二月(小)廿四"},{"title":"2013年雨水时间是 2013年02月18日 20:01:35 农历： 正月(大)初九"},{"title":"2013年驚蟄时间是 2013年03月05日 18:14:51 农历： 正月(大)廿四"},{"title":"2013年春分时间是 2013年03月20日 19:01:55 农历： 二月(小)初九"},{"title":"2013年清明时间是 2013年04月04日 23:02:27 农历： 二月(小)廿四"},{"title":"2013年穀雨时间是 2013年04月20日 06:03:18 农历： 三月(大)十一"},{"title":"2013年立夏时间是 2013年05月05日 16:18:09 农历： 三月(大)廿六"},{"title":"2013年小滿时间是 2013年05月21日 05:09:30 农历： 四月(小)十二"},{"title":"2013年芒種时间是 2013年06月05日 20:23:19 农历： 四月(小)廿七"},{"title":"2013年夏至时间是 2013年06月21日 13:03:56 农历： 五月(大)十四"},{"title":"2013年小暑时间是 2013年07月07日 06:34:36 农历： 五月(大)三十"},{"title":"2013年大暑时间是 2013年07月22日 23:55:58 农历： 六月(大)十五"},{"title":"2013年立秋时间是 2013年08月07日 16:20:21 农历： 七月(小)初一"},{"title":"2013年處暑时间是 2013年08月23日 07:01:41 农历： 七月(小)十七"},{"title":"2013年白露时间是 2013年09月07日 19:16:16 农历： 八月(大)初三"},{"title":"2013年秋分时间是 2013年09月23日 04:44:08 农历： 八月(大)十九"},{"title":"2013年寒露时间是 2013年10月08日 10:58:29 农历： 九月(小)初四"},{"title":"2013年霜降时间是 2013年10月23日 14:09:48 农历： 九月(小)十九"},{"title":"2013年立冬时间是 2013年11月07日 14:13:52 农历： 十月(大)初五"},{"title":"2013年小雪时间是 2013年11月22日 11:48:06 农历： 十月(大)二十"},{"title":"2013年大雪时间是 2013年12月07日 07:08:31 农历： 十一月(小)初五"},{"title":"2013年冬至时间是 2013年12月22日 01:10:59 农历： 十一月(小)二十"},{"title":"2013年小寒时间是 2013年01月05日 12:33:37 农历： 十一月(大)廿四"},{"title":"2013年大寒时间是 2013年01月20日 05:51:42 农历： 十二月(小)初九"},{"title":"2012年冬至时间是 2012年12月21日 19:11:35 农历： 十一月(大)初九"},{"title":"2012年小寒时间是 2012年01月06日 06:43:54 农历： 十二月(小)十三"},{"title":"2012年大寒时间是 2012年01月21日 00:09:49 农历： 十二月(小)廿八"}]