[{"title":"2020年立春时间是 2020年02月04日 17:03:12 农历： 正月(小)十一"},{"title":"2020年雨水时间是 2020年02月19日 12:56:53 农历： 正月(小)廿六"},{"title":"2020年驚蟄时间是 2020年03月05日 10:56:44 农历： 二月(大)十二"},{"title":"2020年春分时间是 2020年03月20日 11:49:29 农历： 二月(大)廿七"},{"title":"2020年清明时间是 2020年04月04日 15:38:02 农历： 三月(大)十二"},{"title":"2020年穀雨时间是 2020年04月19日 22:45:21 农历： 三月(大)廿七"},{"title":"2020年立夏时间是 2020年05月05日 08:51:16 农历： 四月(大)十三"},{"title":"2020年小滿时间是 2020年05月20日 21:49:09 农历： 四月(大)廿八"},{"title":"2020年芒種时间是 2020年06月05日 12:58:18 农历： 四月(大)十四"},{"title":"2020年夏至时间是 2020年06月21日 05:43:33 农历： 四月(大)三十"},{"title":"2020年小暑时间是 2020年07月06日 23:14:20 农历： 五月(小)十五"},{"title":"2020年大暑时间是 2020年07月22日 16:36:44 农历： 六月(小)初二"},{"title":"2020年立秋时间是 2020年08月07日 09:06:03 农历： 六月(小)十八"},{"title":"2020年處暑时间是 2020年08月22日 23:44:48 农历： 七月(大)初四"},{"title":"2020年白露时间是 2020年09月07日 12:07:54 农历： 七月(大)二十"},{"title":"2020年秋分时间是 2020年09月22日 21:30:32 农历： 八月(小)初五"},{"title":"2020年寒露时间是 2020年10月08日 03:55:07 农历： 八月(小)廿一"},{"title":"2020年霜降时间是 2020年10月23日 06:59:25 农历： 九月(大)初七"},{"title":"2020年立冬时间是 2020年11月07日 07:13:46 农历： 九月(大)廿二"},{"title":"2020年小雪时间是 2020年11月22日 04:39:38 农历： 十月(小)初七"},{"title":"2020年大雪时间是 2020年12月07日 00:09:21 农历： 十月(小)廿二"},{"title":"2020年冬至时间是 2020年12月21日 18:02:12 农历： 十一月(小)初七"},{"title":"2020年小寒时间是 2020年01月06日 05:29:59 农历： 十二月(大)十三"},{"title":"2020年大寒时间是 2020年01月20日 22:54:33 农历： 十二月(大)廿七"},{"title":"2019年冬至时间是 2019年12月22日 12:19:18 农历： 十一月(小)廿七"},{"title":"2019年小寒时间是 2019年01月05日 23:38:52 农历： 十一月(大)三十"},{"title":"2019年大寒时间是 2019年01月20日 16:59:27 农历： 十二月(大)十五"}]